monocle_map-0.1.7.dist-info/metadata.json
monocle_map-0.1.7.dist-info/WHEEL
monocle_map-0.1.7.dist-info/METADATA
monocle_map-0.1.7.dist-info/top_level.txt
monocle_map-0.1.7.dist-info/DESCRIPTION.rst
monocle_map-0.1.7.dist-info/RECORD
monocle_map/widgets.py
monocle_map/__init__.py
monocle_map/models.py
monocle_map/monocle.py
monocle_map/admin.py
monocle_map/templates/monocle_map/monocle_map.html
monocle_map/fixtures/monocle_map.json
monocle_map/fixtures/monocle_map/marker.ico
monocle_map/static/monocle_map/monocle_map_admin.css
monocle_map/static/monocle_map/monocle_map_admin.js
monocle_map/static/monocle_map/monocle_map.css
monocle_map/static/monocle_map/monocle_map.js
